freeports_analysis/.DS_Store
freeports_analysis/__init__.py
freeports_analysis/cmd.py
freeports_analysis/conf_parse.py
freeports_analysis/consts.py
freeports_analysis/download.py
freeports_analysis/i18n.py
freeports_analysis/logging.py
freeports_analysis/main.py
freeports_analysis/data/.gitignore
freeports_analysis/data/__init__.py
freeports_analysis/data/companies.csv
freeports_analysis/data/companies_additional_buds.csv
freeports_analysis/data/companies_additional_regexs.csv
freeports_analysis/data/company_to_list.csv
freeports_analysis/data/lists.csv
freeports_analysis/data/markets.csv
freeports_analysis/data/tickers.csv
freeports_analysis/formats/__init__.py
freeports_analysis/formats/algorithms/.gitignore
freeports_analysis/formats/algorithms/__init__.py
freeports_analysis/formats/algorithms/commons.py
freeports_analysis/formats/algorithms/semistructured/__init__.py
freeports_analysis/formats/algorithms/semistructured/formats_mapping.csv
freeports_analysis/formats/algorithms/semistructured/deserialize/__init__.py
freeports_analysis/formats/algorithms/semistructured/deserialize/args.yaml
freeports_analysis/formats/algorithms/semistructured/pdf_filter/__init__.py
freeports_analysis/formats/algorithms/semistructured/pdf_filter/args.yaml
freeports_analysis/formats/algorithms/semistructured/text_extract/__init__.py
freeports_analysis/formats/algorithms/semistructured/text_extract/args.yaml
freeports_analysis/formats/algorithms/structured/__init__.py
freeports_analysis/formats/algorithms/structured/additional_args.csv
freeports_analysis/formats/algorithms/structured/additional_headers.csv
freeports_analysis/formats/algorithms/structured/args.csv
freeports_analysis/formats/algorithms/structured/deselection_lists.csv
freeports_analysis/formats/algorithms/structured/partial_pipes.csv
freeports_analysis/formats/algorithms/unstructured/__init__.py
freeports_analysis/formats/algorithms/unstructured/anima_en23.py
freeports_analysis-0.1.2.dist-info/licenses/LICENSE
freeports_analysis-0.1.2.dist-info/METADATA
freeports_analysis-0.1.2.dist-info/WHEEL
freeports_analysis-0.1.2.dist-info/entry_points.txt
freeports_analysis-0.1.2.dist-info/top_level.txt
freeports_analysis-0.1.2.dist-info/RECORD
