Metadata-Version: 2.4
Name: freeports_analysis
Version: 0.1.2
Summary: Script for dumping a csv from different finance reports about ethical aspects
Author-email: Oreste Sciacqualegni <orestesciacqualegni@tutanota.com>
Maintainer-email: Oreste Sciacqualegni <orestesciacqualegni@tutanota.com>
License-Expression: GPL-3.0
Project-URL: github, https://github.com/tvp-freeports/analysis_finance_reports
Project-URL: documentation, https://docs.freeports.org
Project-URL: homepage, https://www.freeports.org
Keywords: finance,pdf,ethic,economy,datascience
Requires-Python: >=3.8
License-File: LICENSE
Requires-Dist: PyXDG
Requires-Dist: importlib_resources
Requires-Dist: rapidfuzz
Requires-Dist: dotenv
Requires-Dist: pyyaml
Requires-Dist: pandas
Requires-Dist: requests
Requires-Dist: PyMuPDF
Requires-Dist: lxml
Requires-Dist: pydantic
Requires-Dist: pandera
Requires-Dist: portion
Requires-Dist: shapely
Dynamic: license-file
